mpltern/__init__.py
mpltern/_ternary_parsers.py
mpltern/datasets.py
mpltern/hexbin_helpers.py
mpltern/tribin_helpers.py
mpltern/ternary/__init__.py
mpltern/ternary/_axes.py
mpltern/ternary/_base.py
mpltern/ternary/axis.py
mpltern/ternary/datasets.py
mpltern/ternary/spines.py
mpltern/ternary/tick.py
mpltern/ternary/transforms.py
mpltern-1.0.4.dist-info/LICENSE
mpltern-1.0.4.dist-info/METADATA
mpltern-1.0.4.dist-info/WHEEL
mpltern-1.0.4.dist-info/top_level.txt
mpltern-1.0.4.dist-info/RECORD
