Metadata-Version: 2.1
Name: mpltern
Version: 1.0.4
Summary: Ternary plots as projections of Matplotlib
Home-page: https://github.com/yuzie007/mpltern
Author: Yuji Ikeda
Author-email: yuji.ikeda.ac.jp@gmail.com
Project-URL: Bug Reports, https://github.com/yuzie007/mpltern/issues
Project-URL: Source, https://github.com/yuzie007/mpltern
Classifier: Development Status :: 5 - Production/Stable
Classifier: Framework :: Matplotlib
Classifier: Intended Audience :: Science/Research
Classifier: Intended Audience :: Education
Classifier: License :: OSI Approved :: MIT License
Classifier: Programming Language :: Python :: 3
Classifier: Topic :: Scientific/Engineering :: Visualization
Requires-Python: >=3.7
License-File: LICENSE
Requires-Dist: matplotlib>=3.4.0
